{
  "$schema": "https://ui.shadcn.com/schema/registry-item.json",
  "name": "accordion-nested",
  "type": "registry:ui",
  "title": "Nested Accordion",
  "description": "An accordion that supports nested sub-accordions for hierarchical content organization.",
  "registryDependencies": [
    "accordion"
  ],
  "files": [
    {
      "path": "registry/ruixenui/accordion-nested.tsx",
      "content": "\"use client\";\n\nimport {\n  Accordion,\n  AccordionContent,\n  AccordionItem,\n  AccordionTrigger,\n} from \"@/components/ui/accordion\";\n\nexport interface AccordionNestedSubItem {\n  id: string;\n  title: string;\n  content: string;\n}\n\nexport interface AccordionNestedItem {\n  id: string;\n  title: string;\n  content?: string;\n  subItems?: AccordionNestedSubItem[];\n}\n\ninterface AccordionNestedProps {\n  items: AccordionNestedItem[];\n  defaultValue?: string;\n  className?: string;\n}\n\nexport default function AccordionNested({\n  items,\n  defaultValue,\n  className,\n}: AccordionNestedProps) {\n  return (\n    <Accordion\n      type=\"single\"\n      collapsible\n      defaultValue={defaultValue}\n      className={className}\n    >\n      {items.map((item) => (\n        <AccordionItem key={item.id} value={item.id}>\n          <AccordionTrigger className=\"text-left text-[15px] hover:no-underline\">\n            {item.title}\n          </AccordionTrigger>\n          <AccordionContent>\n            {item.content && (\n              <p className=\"text-muted-foreground mb-3\">{item.content}</p>\n            )}\n            {item.subItems && item.subItems.length > 0 && (\n              <Accordion type=\"single\" collapsible className=\"ps-4 border-s\">\n                {item.subItems.map((subItem) => (\n                  <AccordionItem key={subItem.id} value={subItem.id}>\n                    <AccordionTrigger className=\"text-left text-sm hover:no-underline py-2\">\n                      {subItem.title}\n                    </AccordionTrigger>\n                    <AccordionContent className=\"text-muted-foreground text-sm\">\n                      {subItem.content}\n                    </AccordionContent>\n                  </AccordionItem>\n                ))}\n              </Accordion>\n            )}\n          </AccordionContent>\n        </AccordionItem>\n      ))}\n    </Accordion>\n  );\n}\n",
      "type": "registry:ui",
      "target": "components/ruixen/accordion-nested.tsx"
    }
  ]
}