{
  "$schema": "https://ui.shadcn.com/schema/registry-item.json",
  "name": "aurora-flow-demo",
  "type": "registry:example",
  "title": "Aurora Flow Demo",
  "description": "Example showing a beautiful aurora-style background with flowing gradients.",
  "registryDependencies": [
    "https://ruixen.com/r/aurora-flow"
  ],
  "files": [
    {
      "path": "registry/example/aurora-flow-demo.tsx",
      "content": "import AuroraFlow from \"@/registry/ruixenui/aurora-flow\";\n\nexport default function DemoOne() {\n  return (\n    <main className=\"flex flex-col justify-center items-cennter rounded-xl\">\n      <AuroraFlow />\n    </main>\n  );\n}\n",
      "type": "registry:example",
      "target": "components/aurora-flow-demo.tsx"
    }
  ]
}