{
  "$schema": "https://ui.shadcn.com/schema/registry-item.json",
  "name": "checkbox-card",
  "type": "registry:ui",
  "title": "Checkbox Card",
  "description": "A card-style checkbox with icon, title, and description for rich selections.",
  "dependencies": [
    "lucide-react"
  ],
  "files": [
    {
      "path": "registry/ruixenui/checkbox-card.tsx",
      "content": "\"use client\";\n\nimport * as React from \"react\";\nimport { cn } from \"@/lib/utils\";\nimport { Check } from \"lucide-react\";\n\ninterface CheckboxCardProps {\n  checked?: boolean;\n  defaultChecked?: boolean;\n  onCheckedChange?: (checked: boolean) => void;\n  title: string;\n  description?: string;\n  icon?: React.ReactNode;\n  disabled?: boolean;\n  id?: string;\n  className?: string;\n}\n\nexport default function CheckboxCard({\n  checked,\n  defaultChecked = false,\n  onCheckedChange,\n  title,\n  description,\n  icon,\n  disabled = false,\n  id,\n  className,\n}: CheckboxCardProps) {\n  const [internalChecked, setInternalChecked] = React.useState(defaultChecked);\n  const isControlled = checked !== undefined;\n  const isChecked = isControlled ? checked : internalChecked;\n  const inputId = id || React.useId();\n\n  const handleChange = (e: React.ChangeEvent<HTMLInputElement>) => {\n    const newChecked = e.target.checked;\n    if (!isControlled) {\n      setInternalChecked(newChecked);\n    }\n    onCheckedChange?.(newChecked);\n  };\n\n  return (\n    <label\n      htmlFor={inputId}\n      className={cn(\n        \"group relative flex cursor-pointer items-start gap-4 rounded-xl border-2 p-4 transition-all duration-200\",\n        isChecked\n          ? \"border-primary bg-primary/5\"\n          : \"border-border bg-background hover:border-muted-foreground/50\",\n        disabled && \"cursor-not-allowed opacity-50\",\n        className,\n      )}\n    >\n      <input\n        type=\"checkbox\"\n        id={inputId}\n        checked={isChecked}\n        onChange={handleChange}\n        disabled={disabled}\n        className=\"peer sr-only\"\n      />\n      {icon && (\n        <div\n          className={cn(\n            \"flex h-10 w-10 shrink-0 items-center justify-center rounded-lg transition-colors\",\n            isChecked\n              ? \"bg-primary text-primary-foreground\"\n              : \"bg-muted text-muted-foreground\",\n          )}\n        >\n          {icon}\n        </div>\n      )}\n      <div className=\"flex flex-1 flex-col gap-1\">\n        <span className=\"text-sm font-semibold text-foreground\">{title}</span>\n        {description && (\n          <span className=\"text-sm text-muted-foreground\">{description}</span>\n        )}\n      </div>\n      <div\n        className={cn(\n          \"flex h-5 w-5 shrink-0 items-center justify-center rounded-full border-2 transition-all duration-200\",\n          isChecked\n            ? \"border-primary bg-primary text-primary-foreground\"\n            : \"border-muted-foreground/30 bg-background\",\n        )}\n      >\n        {isChecked && <Check className=\"size-3 stroke-[3]\" />}\n      </div>\n    </label>\n  );\n}\n\nexport { CheckboxCard, type CheckboxCardProps };\n",
      "type": "registry:ui",
      "target": "components/ruixen/checkbox-card.tsx"
    }
  ]
}