{
  "$schema": "https://ui.shadcn.com/schema/registry-item.json",
  "name": "table-edit-demo",
  "type": "registry:example",
  "title": "Table Edit Demo",
  "description": "Example showing an editable table component with inline editing and dropdown menus.",
  "registryDependencies": [
    "https://www.ruixen.com/r/table-edit"
  ],
  "files": [
    {
      "path": "registry/example/table-edit-demo.tsx",
      "content": "\"use client\";\n\nimport { useState } from \"react\";\nimport ConfigurableEditableTable, {\n  User,\n} from \"@/registry/ruixenui/table-edit\";\nimport { Button } from \"@/components/ui/button\";\n\nexport default function TableDemoPage() {\n  const customData: User[] = [\n    {\n      id: \"101\",\n      name: \"Liam Johnson\",\n      email: \"liam.j@custom.com\",\n      role: \"Developer\",\n      status: \"Active\",\n      balance: \"$1,500.00\",\n    },\n    {\n      id: \"102\",\n      name: \"Emma Brown\",\n      email: \"emma.b@custom.com\",\n      role: \"Designer\",\n      status: \"Inactive\",\n      balance: \"$700.00\",\n    },\n    {\n      id: \"103\",\n      name: \"Noah Smith\",\n      email: \"noah.s@custom.com\",\n      role: \"Manager\",\n      status: \"Active\",\n      balance: \"$2,000.00\",\n    },\n  ];\n\n  const [useCustom, setUseCustom] = useState(false);\n\n  return (\n    <div className=\"p-8 space-y-6\">\n      <h1 className=\"text-2xl font-bold\">Configurable Editable Table Demo</h1>\n\n      <div className=\"flex gap-4\">\n        <Button\n          onClick={() => setUseCustom(false)}\n          variant={useCustom ? \"outline\" : \"default\"}\n        >\n          Use Default Data\n        </Button>\n        <Button\n          onClick={() => setUseCustom(true)}\n          variant={useCustom ? \"default\" : \"outline\"}\n        >\n          Use Custom Data\n        </Button>\n      </div>\n\n      <ConfigurableEditableTable\n        data={useCustom ? customData : undefined}\n        footerTotal={useCustom ? \"$4,200.00\" : undefined}\n      />\n    </div>\n  );\n}\n",
      "type": "registry:example",
      "target": "components/table-edit-demo.tsx"
    }
  ]
}